makelabel.py
makelabel-0.1.dist-info/entry_points.txt
makelabel-0.1.dist-info/licenses/LICENSE
makelabel-0.1.dist-info/WHEEL
makelabel-0.1.dist-info/METADATA
makelabel-0.1.dist-info/RECORD
