Metadata-Version: 2.4
Name: makelabel
Version: 0.1
Summary: Generate a label from the given text.
Author-email: Julien Palard <julien@palard.fr>
License-Expression: MIT
License-File: LICENSE
Requires-Dist: pillow
Requires-Dist: black ; extra == "dev"
Requires-Dist: isort ; extra == "dev"
Project-URL: Home, https://git.afpy.org/mdk/makelabel
Provides-Extra: dev
